build/lib/confidence/__init__.py
build/lib/confidence/_version.py
build/lib/confidence/confidence.py
build/lib/confidence/errors.py
build/lib/confidence/flag_types.py
build/lib/confidence/names.py
build/lib/confidence/openfeature_provider.py
build/lib/confidence/telemetry.py
build/lib/confidence/telemetry_pb2.py
build/lib/tests/__init__.py
build/lib/tests/test_confidence.py
build/lib/tests/test_logging.py
build/lib/tests/test_names.py
build/lib/tests/test_provider.py
build/lib/tests/test_provider_parametrized.py
build/lib/tests/test_telemetry.py
confidence/__init__.py
confidence/_version.py
confidence/confidence.py
confidence/errors.py
confidence/flag_types.py
confidence/names.py
confidence/openfeature_provider.py
confidence/telemetry.proto
confidence/telemetry.py
confidence/telemetry_pb2.py
spotify_confidence_sdk-2.0.2.dist-info/licenses/LICENSE
tests/__init__.py
tests/test_confidence.py
tests/test_logging.py
tests/test_names.py
tests/test_provider.py
tests/test_provider_parametrized.py
tests/test_telemetry.py
spotify_confidence_sdk-2.0.2.dist-info/METADATA
spotify_confidence_sdk-2.0.2.dist-info/WHEEL
spotify_confidence_sdk-2.0.2.dist-info/top_level.txt
spotify_confidence_sdk-2.0.2.dist-info/RECORD
