Metadata-Version: 2.4
Name: spotify_confidence_sdk
Version: 2.0.2
Summary: Confidence provider for the OpenFeature SDK
Author: Confidence team
License: 
Project-URL: Homepage, https://github.com/spotify/confidence-sdk-python
Classifier: Programming Language :: Python
Classifier: Programming Language :: Python :: 3
Requires-Python: >=3.9
License-File: LICENSE
Requires-Dist: requests==2.32.4
Requires-Dist: openfeature-sdk==0.4.2
Requires-Dist: typing_extensions<5.0.0,>=4.9.0
Requires-Dist: httpx==0.27.2
Requires-Dist: protobuf<7.0.0,>=5.29.5
Provides-Extra: dev
Requires-Dist: pytest==7.4.2; extra == "dev"
Requires-Dist: pytest-mock==3.11.1; extra == "dev"
Requires-Dist: black==23.9.1; extra == "dev"
Requires-Dist: flake8==6.1.0; extra == "dev"
Requires-Dist: requests_mock==1.11.0; extra == "dev"
Requires-Dist: setuptools_scm==8.0.4; extra == "dev"
Requires-Dist: mypy==1.5.1; extra == "dev"
Requires-Dist: python-dotenv==1.0.1; extra == "dev"
Dynamic: license-file
